netcov/__init__.py
netcov/coverage.py
netcov/hook.py
netcov/visual.py
netcov/algorithm/__init__.py
netcov/algorithm/construct.py
netcov/algorithm/converttrace.py
netcov/algorithm/coverage.py
netcov/algorithm/templates.py
netcov/algorithm/testsuite.py
netcov/algorithm/utils.py
netcov/datamodel/__init__.py
netcov/datamodel/batchmanager.py
netcov/datamodel/configtypes.py
netcov/datamodel/dnode.py
netcov/datamodel/ifg.py
netcov/datamodel/netstate.py
netcov/datamodel/network.py
netcov/datamodel/sortedrib.py
netcov/datamodel/sourcelines.py
netcov/datamodel/template.py
netcov/datamodel/utils.py
netcov-0.2.0.dist-info/LICENSE.txt
netcov-0.2.0.dist-info/METADATA
netcov-0.2.0.dist-info/WHEEL
netcov-0.2.0.dist-info/top_level.txt
netcov-0.2.0.dist-info/RECORD
