Metadata-Version: 2.1
Name: netcov
Version: 0.2.0
Summary: Coverage analyzer for network router configurations
Author: Xieyang Xu
Author-email: Xieyang Xu <ashlippers@gmail.com>
License: Apache License
Project-URL: Homepage, https://github.com/UWNetworksLab/netcov
Project-URL: Bug Tracker, https://github.com/UWNetworksLab/netcov/issues
Classifier: Programming Language :: Python :: 3
Classifier: Programming Language :: Python :: 3 :: Only
Classifier: Programming Language :: Python :: 3.7
Classifier: License :: OSI Approved :: Apache Software License
Classifier: Operating System :: OS Independent
Requires-Python: >=3.7
License-File: LICENSE.txt
Requires-Dist: pandas
Requires-Dist: pickle-mixin
Requires-Dist: networkx
Requires-Dist: pyvis
Requires-Dist: treelib
Requires-Dist: dd
Requires-Dist: parse
Requires-Dist: numpy
Requires-Dist: ipaddress
Requires-Dist: pybatfish
